ninja_vs_zombies/__init__.py
ninja_vs_zombies/ninja.py
ninja_vs_zombies-0.0.5.dist-info/LICENSE.txt
ninja_vs_zombies-0.0.5.dist-info/METADATA
ninja_vs_zombies-0.0.5.dist-info/WHEEL
ninja_vs_zombies-0.0.5.dist-info/top_level.txt
ninja_vs_zombies-0.0.5.dist-info/RECORD
