Metadata-Version: 2.1
Name: ninja-vs-zombies
Version: 0.0.5
Summary: Um projeto de jogo de plataforma em pygame
Home-page: https://github.com/adrianmartinez-cg/ninjavszombies
Author: Pedro Adrian Pereira Martinez
Author-email: pedro.martinez@ccc.ufcg.edu.br
License: MIT
Platform: UNKNOWN
Classifier: Programming Language :: Python :: 3
Classifier: License :: OSI Approved :: MIT License
Classifier: Operating System :: OS Independent
Requires-Python: >=3.6
